ragger_simple/__init__.py
ragger_simple/cli.py
ragger_simple/db.py
ragger_simple-0.2.0.dist-info/licenses/LICENSE
ragger_simple-0.2.0.dist-info/METADATA
ragger_simple-0.2.0.dist-info/WHEEL
ragger_simple-0.2.0.dist-info/entry_points.txt
ragger_simple-0.2.0.dist-info/top_level.txt
ragger_simple-0.2.0.dist-info/RECORD
