Metadata-Version: 2.4
Name: ragger-simple
Version: 0.2.0
Summary: Simple vector database operations with Qdrant
Home-page: https://github.com/HMCorp-Fund/ragger-simple
Author: Anton Pavlenko
Author-email: apavlenko@hmcorp.fund
Classifier: Programming Language :: Python :: 3
Classifier: License :: OSI Approved :: MIT License
Classifier: Operating System :: OS Independent
Requires-Python: >=3.7
License-File: LICENSE
Requires-Dist: sentence-transformers>=2.0.0
Requires-Dist: qdrant-client>=1.0.0
Requires-Dist: numpy>=1.20.0
Dynamic: author
Dynamic: author-email
Dynamic: classifier
Dynamic: description
Dynamic: description-content-type
Dynamic: home-page
Dynamic: license-file
Dynamic: requires-dist
Dynamic: requires-python
Dynamic: summary
